cleverbot/__init__.py
cleverbot/__main__.py
cleverbot/cleverbot.py
cleverbot/constants.py
cleverbot/main.py
cleverbot_scraper-0.2.7.dist-info/LICENSE
cleverbot_scraper-0.2.7.dist-info/METADATA
cleverbot_scraper-0.2.7.dist-info/WHEEL
cleverbot_scraper-0.2.7.dist-info/top_level.txt
cleverbot_scraper-0.2.7.dist-info/RECORD
