Metadata-Version: 2.1
Name: cleverbot-scraper
Version: 0.2.7
Summary: Free cleverbot without headless browser
Home-page: https://github.com/matheusfillipe/cleverbot_scraper
Author: Matheus Fillipe
Author-email: mattf@tilde.club
License: UNKNOWN
Platform: UNKNOWN
Classifier: Development Status :: 5 - Production/Stable
Classifier: Programming Language :: Python :: 3
Classifier: License :: OSI Approved :: MIT License
Classifier: Operating System :: OS Independent
Classifier: Topic :: Software Development :: Libraries :: Python Modules
Classifier: Topic :: Communications :: Chat
Classifier: Topic :: Internet
Requires-Python: >=3.4
License-File: LICENSE
Requires-Dist: requests
